dbt_workflows_factory/__init__.py
dbt_workflows_factory/cli.py
dbt_workflows_factory/dbt_workflows_converter.py
dbt_workflows_factory/params.py
dbt_workflows_factory/tasks.py
dbt_workflows_factory/yaml_builder.py
dbt_workflows_factory-0.2.0.dist-info/LICENSE
dbt_workflows_factory-0.2.0.dist-info/METADATA
dbt_workflows_factory-0.2.0.dist-info/WHEEL
dbt_workflows_factory-0.2.0.dist-info/top_level.txt
dbt_workflows_factory-0.2.0.dist-info/RECORD
