Metadata-Version: 2.1
Name: dbt-workflows-factory
Version: 0.2.0
Summary: DBT workflows factory for Google Cloud Platform
Author-email: Piotr Pękala <piotr.pekala@getindata.com>, Piotr Tutak <piotr.tutak@getindata.com>
License: Apache License
Classifier: Development Status :: 3 - Alpha
Classifier: Intended Audience :: Developers
Classifier: License :: OSI Approved :: MIT License
Classifier: Programming Language :: Python :: 3 :: Only
Classifier: Programming Language :: Python :: 3.9
Classifier: Programming Language :: Python :: 3.10
Classifier: Programming Language :: Python :: 3.11
Requires-Python: >=3.9
License-File: LICENSE
Requires-Dist: dbt-graph-builder (>=0.5.0)
Requires-Dist: click (>=8.1.3)
